secureme/__init__.py
secureme-0.0.4.dist-info/LICENCE
secureme-0.0.4.dist-info/METADATA
secureme-0.0.4.dist-info/WHEEL
secureme-0.0.4.dist-info/top_level.txt
secureme-0.0.4.dist-info/RECORD
