Metadata-Version: 2.1
Name: secureme
Version: 0.0.4
Summary: Developed by Developers, Contributed by Contributers.
Home-page: https://github.com/jainamoswal/secureme
Author: Jainam Oswal
Author-email: Jainamoswal@gmail.com
License: MIT
Platform: UNKNOWN
Classifier: Programming Language :: Python :: 3
Classifier: License :: OSI Approved :: MIT License
Classifier: Operating System :: OS Independent
Requires-Python: >=3.6
